src/components/alu/gen_xor.vhdl
library IEEE;
use IEEE.STD_LOGIC_1164.ALL;
use work.constant_package.ALL;

entity gen_xor is 
    generic(
        G_DATA_WIDTH : integer := DATA_WIDTH_GEN
    );
    port (
        pi_op1, pi_op2 : in  std_logic_vector(G_DATA_WIDTH - 1  downto 0);
        
        po_result     : out std_logic_vector(G_DATA_WIDTH - 1  downto 0)
    );
end entity gen_xor;

architecture behavior of gen_xor is begin
    po_result <= pi_op1 xor pi_op2;
end architecture behavior;

src/components/alu/gen_or.vhdl
library IEEE;
use IEEE.STD_LOGIC_1164.ALL;
use work.constant_package.ALL;

entity gen_or is 
    generic(
        G_DATA_WIDTH : integer := DATA_WIDTH_GEN
    );
    port (
        pi_op1, pi_op2 : in  std_logic_vector(G_DATA_WIDTH - 1  downto 0);
        
        po_result     : out std_logic_vector(G_DATA_WIDTH - 1  downto 0)
    );
end entity gen_or;

architecture behavior of gen_or is begin
    po_result <= pi_op1 or pi_op2;
end architecture behavior;

src/components/alu/gen_and.vhdl
library IEEE;
use IEEE.STD_LOGIC_1164.ALL;
use work.constant_package.ALL;

entity gen_and is 
    generic(
        G_DATA_WIDTH : integer := DATA_WIDTH_GEN
    );
    port (
        pi_op1, pi_op2 : in  std_logic_vector(G_DATA_WIDTH - 1  downto 0);
        
        po_result     : out std_logic_vector(G_DATA_WIDTH - 1  downto 0)
    );
end entity gen_and;

architecture behavior of gen_and is begin
    po_result <= pi_op1 and pi_op2;
end architecture behavior;

src/testbenches/alu/gates_tb.vhdl
-- Laboratory GdTi solutions/versuch5
-- Winter Semester 24/25
-- Group Details
-- Lab Date:
-- 1. Participant First and  Last Name: 
-- 2. Participant First and Last Name:
 
 
-- coding conventions
-- g_<name> Generics
-- p_<name> Ports
-- c_<name> Constants
-- s_<name> Signals
-- v_<name> Variables

library IEEE;
use IEEE.STD_LOGIC_1164.ALL;
use IEEE.NUMERIC_STD.ALL;
use work.constant_package.ALL;

entity gates_tb is
end gates_tb;

architecture behavior of gates_tb is
    signal s_in1, s_in2 : STD_LOGIC_VECTOR(DATA_WIDTH_GEN - 1 downto 0) := (others => '0');
    signal s_result_and, s_result_or, s_result_xor : STD_LOGIC_VECTOR(DATA_WIDTH_GEN - 1 downto 0) := (others => '0');
    signal s_result_expected : STD_LOGIC_VECTOR(DATA_WIDTH_GEN - 1 downto 0) := (others => '0');
    constant c_period : time := 10 ns;

    begin 
        AND_UNIT: entity work.gen_and generic map (G_DATA_WIDTH => DATA_WIDTH_GEN) port map (s_in1, s_in2, s_result_and);
        OR_UNIT: entity work.gen_or generic map (G_DATA_WIDTH => DATA_WIDTH_GEN) port map (s_in1, s_in2, s_result_or);
        XOR_UNIT: entity work.gen_xor generic map (G_DATA_WIDTH => DATA_WIDTH_GEN) port map (s_in1, s_in2, s_result_xor);

    process 
    begin 

        s_in1 <= std_logic_vector(to_unsigned(8, DATA_WIDTH_GEN));
        s_in2 <= std_logic_vector(to_unsigned(4, DATA_WIDTH_GEN));

        wait for c_period/2;

        -- AND 
        s_result_expected <= s_in1 and s_in2;  
        wait for c_period/2; -- Wait for one clock cycle
        assert(s_result_expected = s_result_and) report "Had error in AND-Function " severity error;
        
        -- OR 
        s_result_expected <= s_in1 or s_in2;  
        wait for c_period/2; -- Wait for one clock cycle
        assert(s_result_expected = s_result_or) report "Had error in OR-Function " severity error;

        -- XOR 
        s_result_expected <= s_in1 xor s_in2;  
        wait for c_period/2; -- Wait for one clock cycle
        assert(s_result_expected = s_result_xor) report "Had error in XOR-Function " severity error;
    
        wait for c_period/2;
        
        s_in1 <= std_logic_vector(to_unsigned(0, DATA_WIDTH_GEN));
        s_in2 <= std_logic_vector(to_unsigned(0, DATA_WIDTH_GEN));

        wait for c_period/2;

        -- AND 
        s_result_expected <= s_in1 and s_in2;  
        wait for c_period/2; -- Wait for one clock cycle
        assert(s_result_expected = s_result_and) report "Had error in AND-Function " severity error;
        
        -- OR 
        s_result_expected <= s_in1 or s_in2;  
        wait for c_period/2; -- Wait for one clock cycle
        assert(s_result_expected = s_result_or) report "Had error in OR-Function " severity error;

        -- XOR 
        s_result_expected <= s_in1 xor s_in2;  
        wait for c_period/2; -- Wait for one clock cycle
        assert(s_result_expected = s_result_xor) report "Had error in XOR-Function " severity error;
    
        wait for c_period/2;
         
        s_in1 <= std_logic_vector(to_unsigned(2**DATA_WIDTH_GEN-1, DATA_WIDTH_GEN));
        s_in2 <= std_logic_vector(to_unsigned(0, DATA_WIDTH_GEN));

        wait for c_period/2;

        -- AND 
        s_result_expected <= s_in1 and s_in2;  
        wait for c_period/2; -- Wait for one clock cycle
        assert(s_result_expected = s_result_and) report "Had error in AND-Function " severity error;
        
        -- OR 
        s_result_expected <= s_in1 or s_in2;  
        wait for c_period/2; -- Wait for one clock cycle
        assert(s_result_expected = s_result_or) report "Had error in OR-Function " severity error;

        -- XOR 
        s_result_expected <= s_in1 xor s_in2;  
        wait for c_period/2; -- Wait for one clock cycle
        assert(s_result_expected = s_result_xor) report "Had error in XOR-Function " severity error;
    
        wait for c_period/2;
    
        s_in1 <= std_logic_vector(to_unsigned(0, DATA_WIDTH_GEN));
        s_in2 <= std_logic_vector(to_unsigned(2**DATA_WIDTH_GEN-1, DATA_WIDTH_GEN));

        wait for c_period/2;

        -- AND 
        s_result_expected <= s_in1 and s_in2;  
        wait for c_period/2; -- Wait for one clock cycle
        assert(s_result_expected = s_result_and) report "Had error in AND-Function " severity error;
        
        -- OR 
        s_result_expected <= s_in1 or s_in2;  
        wait for c_period/2; -- Wait for one clock cycle
        assert(s_result_expected = s_result_or) report "Had error in OR-Function " severity error;

        -- XOR 
        s_result_expected <= s_in1 xor s_in2;  
        wait for c_period/2; -- Wait for one clock cycle
        assert(s_result_expected = s_result_xor) report "Had error in XOR-Function " severity error;
    
        wait for c_period/2;

        s_in1 <= std_logic_vector(to_unsigned(2**DATA_WIDTH_GEN-1, DATA_WIDTH_GEN));
        s_in2 <= std_logic_vector(to_unsigned(2**DATA_WIDTH_GEN-1, DATA_WIDTH_GEN));

        wait for c_period/2;

        -- AND 
        s_result_expected <= s_in1 and s_in2;  
        wait for c_period/2; -- Wait for one clock cycle
        assert(s_result_expected = s_result_and) report "Had error in AND-Function " severity error;
        
        -- OR 
        s_result_expected <= s_in1 or s_in2;  
        wait for c_period/2; -- Wait for one clock cycle
        assert(s_result_expected = s_result_or) report "Had error in OR-Function " severity error;

        -- XOR 
        s_result_expected <= s_in1 xor s_in2;  
        wait for c_period/2; -- Wait for one clock cycle
        assert(s_result_expected = s_result_xor) report "Had error in XOR-Function " severity error;
    
        wait for c_period/2;

        s_in1 <= std_logic_vector(to_unsigned(15, DATA_WIDTH_GEN));
        s_in2 <= std_logic_vector(to_unsigned(11, DATA_WIDTH_GEN));

        wait for c_period/2;

        -- AND 
        s_result_expected <= s_in1 and s_in2;  
        wait for c_period/2; -- Wait for one clock cycle
        assert(s_result_expected = s_result_and) report "Had error in AND-Function " severity error;
        
        -- OR 
        s_result_expected <= s_in1 or s_in2;  
        wait for c_period/2; -- Wait for one clock cycle
        assert(s_result_expected = s_result_or) report "Had error in OR-Function " severity error;

        -- XOR 
        s_result_expected <= s_in1 xor s_in2;  
        wait for c_period/2; -- Wait for one clock cycle
        assert(s_result_expected = s_result_xor) report "Had error in XOR-Function " severity error;
    
        wait for c_period/2;
        
        assert false report "end of test" severity note;
        wait; 

    end process;

end architecture behavior;

src/vcd/gates_tb.vcd
$date
  Thu Apr 24 14:10:20 2025
$end
$version
  GHDL v0
$end
$timescale
  1 fs
$end
$scope module standard $end
$upscope $end
$scope module std_logic_1164 $end
$upscope $end
$scope module numeric_std $end
$upscope $end
$scope module constant_package $end
$upscope $end
$scope module gates_tb $end
$var reg 8 ! s_in1[7:0] $end
$var reg 8 " s_in2[7:0] $end
$var reg 8 # s_result_and[7:0] $end
$var reg 8 $ s_result_or[7:0] $end
$var reg 8 % s_result_xor[7:0] $end
$var reg 8 & s_result_expected[7:0] $end
$scope module and_unit $end
$var reg 8 ' pi_op1[7:0] $end
$var reg 8 ( pi_op2[7:0] $end
$var reg 8 ) po_result[7:0] $end
$upscope $end
$scope module or_unit $end
$var reg 8 * pi_op1[7:0] $end
$var reg 8 + pi_op2[7:0] $end
$var reg 8 , po_result[7:0] $end
$upscope $end
$scope module xor_unit $end
$var reg 8 - pi_op1[7:0] $end
$var reg 8 . pi_op2[7:0] $end
$var reg 8 / po_result[7:0] $end
$upscope $end
$upscope $end
$enddefinitions $end
#0
b00001000 !
b00000100 "
b00000000 #
b00001100 $
b00001100 %
b00000000 &
b00001000 '
b00000100 (
b00000000 )
b00001000 *
b00000100 +
b00001100 ,
b00001000 -
b00000100 .
b00001100 /
#5000000
#10000000
b00001100 &
#15000000
#20000000
#25000000
b00000000 !
b00000000 "
b00000000 $
b00000000 %
b00000000 '
b00000000 (
b00000000 *
b00000000 +
b00000000 ,
b00000000 -
b00000000 .
b00000000 /
#30000000
b00000000 &
#35000000
#40000000
#45000000
#50000000
b11111111 !
b11111111 $
b11111111 %
b11111111 '
b11111111 *
b11111111 ,
b11111111 -
b11111111 /
#55000000
#60000000
b11111111 &
#65000000
#70000000
#75000000
b00000000 !
b11111111 "
b00000000 '
b11111111 (
b00000000 *
b11111111 +
b00000000 -
b11111111 .
#80000000
b00000000 &
#85000000
b11111111 &
#90000000
#95000000
#100000000
b11111111 !
b11111111 #
b00000000 %
b11111111 '
b11111111 )
b11111111 *
b11111111 -
b00000000 /
#105000000
#110000000
#115000000
b00000000 &
#120000000
#125000000
b00001111 !
b00001011 "
b00001011 #
b00001111 $
b00000100 %
b00001111 '
b00001011 (
b00001011 )
b00001111 *
b00001011 +
b00001111 ,
b00001111 -
b00001011 .
b00000100 /
#130000000
b00001011 &
#135000000
b00001111 &
#140000000
b00000100 &
